cira_ops/__init__.py
cira_ops/_core.cpython-38-x86_64-linux-gnu.so
cira_ops.libs/libgcc_s-0cd532bd.so.1
cira_ops.libs/libstdc++-5d72f927.so.6.0.33
cira_ops-0.2.3.dist-info/METADATA
cira_ops-0.2.3.dist-info/WHEEL
cira_ops-0.2.3.dist-info/top_level.txt
cira_ops-0.2.3.dist-info/RECORD
